captcha_recognizer/__init__.py
captcha_recognizer/slider.py
captcha_recognizer/models/slider.onnx
captcha_recognizer-1.0.1.dist-info/licenses/LICENSE
captcha_recognizer-1.0.1.dist-info/METADATA
captcha_recognizer-1.0.1.dist-info/WHEEL
captcha_recognizer-1.0.1.dist-info/top_level.txt
captcha_recognizer-1.0.1.dist-info/RECORD
