Metadata-Version: 2.4
Name: captcha-recognizer
Version: 1.0.1
Summary: 滑块验证码识别
Home-page: https://github.com/chenwei-zhao/captcha-recognizer
Author: Zhao Chenwei
Author-email: chenwei.zhaozhao@gmail.com
License: MIT
Keywords: captcha,slider,captcha-recognizer,captcha_recognizer,滑块,滑块验证码,滑块识别
Requires-Python: >=3.6
License-File: LICENSE
Requires-Dist: opencv-python
Requires-Dist: shapely
Requires-Dist: onnxruntime
Dynamic: author
Dynamic: author-email
Dynamic: description
Dynamic: description-content-type
Dynamic: home-page
Dynamic: keywords
Dynamic: license
Dynamic: license-file
Dynamic: requires-dist
Dynamic: requires-python
Dynamic: summary
